belton/__init__.py
belton_api-0.1.1.dist-info/METADATA
belton_api-0.1.1.dist-info/WHEEL
belton_api-0.1.1.dist-info/RECORD
