Metadata-Version: 2.3
Name: belton-api
Version: 0.1.1
Summary: CLI for open source framework.
Author: Belton
Author-email: pip@belton.dev
Requires-Python: >=3.13
Classifier: Programming Language :: Python :: 3
Classifier: Programming Language :: Python :: 3.13
Project-URL: Documentation, https://belton.dev/pip/docs
Project-URL: Homepage, https://belton.dev/pip
Project-URL: Repository, https://github.com/belton-dev/belton-pip
